{"index":{"links":{"/":[{"source":"/","target":"/main/about","text":"About Me"},{"source":"/","target":"/main/projects","text":"My Projects"},{"source":"/","target":"/public-knowledge-garden","text":"public knowledge garden"}],"/main/about":[{"source":"/main/about","target":"/Health","text":"Health"},{"source":"/main/about","target":"/Productivity","text":"Productivity"},{"source":"/main/about","target":"/Crypto","text":"Crypto"},{"source":"/main/about","target":"/Amsterdam-Netherlands","text":"Amsterdam, Netherlands"},{"source":"/main/about","target":"/Databricks","text":"Databricks"},{"source":"/main/about","target":"/Moscow","text":"Moscow"},{"source":"/main/about","target":"/Higher-School-of-Economics","text":"Higher School of Economics"},{"source":"/main/about","target":"/Yandex","text":"Yandex"},{"source":"/main/about","target":"/Style-Lab","text":"Style Lab"},{"source":"/main/about","target":"/Amsterdam-Netherlands","text":"Amsterdam, Netherlands"},{"source":"/main/about","target":"/Databricks","text":"Databricks"},{"source":"/main/about","target":"/Databricks","text":"Databricks"},{"source":"/main/about","target":"/Databricks","text":"here"},{"source":"/main/about","target":"/main/projects","text":"side-projects"},{"source":"/main/about","target":"/Summate","text":"Summate"},{"source":"/main/about","target":"/Nights-Weekends-Season-3","text":"Nights \u0026 Weekends Season 3"}]},"backlinks":{"/Amsterdam-Netherlands":[{"source":"/main/about","target":"/Amsterdam-Netherlands","text":"Amsterdam, Netherlands"},{"source":"/main/about","target":"/Amsterdam-Netherlands","text":"Amsterdam, Netherlands"}],"/Crypto":[{"source":"/main/about","target":"/Crypto","text":"Crypto"}],"/Databricks":[{"source":"/main/about","target":"/Databricks","text":"Databricks"},{"source":"/main/about","target":"/Databricks","text":"Databricks"},{"source":"/main/about","target":"/Databricks","text":"Databricks"},{"source":"/main/about","target":"/Databricks","text":"here"}],"/Health":[{"source":"/main/about","target":"/Health","text":"Health"}],"/Higher-School-of-Economics":[{"source":"/main/about","target":"/Higher-School-of-Economics","text":"Higher School of Economics"}],"/Moscow":[{"source":"/main/about","target":"/Moscow","text":"Moscow"}],"/Nights-Weekends-Season-3":[{"source":"/main/about","target":"/Nights-Weekends-Season-3","text":"Nights \u0026 Weekends Season 3"}],"/Productivity":[{"source":"/main/about","target":"/Productivity","text":"Productivity"}],"/Style-Lab":[{"source":"/main/about","target":"/Style-Lab","text":"Style Lab"}],"/Summate":[{"source":"/main/about","target":"/Summate","text":"Summate"}],"/Yandex":[{"source":"/main/about","target":"/Yandex","text":"Yandex"}],"/main/about":[{"source":"/","target":"/main/about","text":"About Me"}],"/main/projects":[{"source":"/","target":"/main/projects","text":"My Projects"},{"source":"/main/about","target":"/main/projects","text":"side-projects"}],"/public-knowledge-garden":[{"source":"/","target":"/public-knowledge-garden","text":"public knowledge garden"}]}},"links":[{"source":"/","target":"/main/about","text":"About Me"},{"source":"/","target":"/main/projects","text":"My Projects"},{"source":"/","target":"/public-knowledge-garden","text":"public knowledge garden"},{"source":"/main/about","target":"/Health","text":"Health"},{"source":"/main/about","target":"/Productivity","text":"Productivity"},{"source":"/main/about","target":"/Crypto","text":"Crypto"},{"source":"/main/about","target":"/Amsterdam-Netherlands","text":"Amsterdam, Netherlands"},{"source":"/main/about","target":"/Databricks","text":"Databricks"},{"source":"/main/about","target":"/Moscow","text":"Moscow"},{"source":"/main/about","target":"/Higher-School-of-Economics","text":"Higher School of Economics"},{"source":"/main/about","target":"/Yandex","text":"Yandex"},{"source":"/main/about","target":"/Style-Lab","text":"Style Lab"},{"source":"/main/about","target":"/Amsterdam-Netherlands","text":"Amsterdam, Netherlands"},{"source":"/main/about","target":"/Databricks","text":"Databricks"},{"source":"/main/about","target":"/Databricks","text":"Databricks"},{"source":"/main/about","target":"/Databricks","text":"here"},{"source":"/main/about","target":"/main/projects","text":"side-projects"},{"source":"/main/about","target":"/Summate","text":"Summate"},{"source":"/main/about","target":"/Nights-Weekends-Season-3","text":"Nights \u0026 Weekends Season 3"}]}